Workbook

Sheet 使い方
B2: 業務効果額 算出シート
B3: 間接部門(運用部・営業事務・総務)の業務が会社の利益にどれだけ効いたかを金額で見える化する
B6: シート構成
B7: 基準値 | C7: 応募1件の価値、営業の時間あたり粗利、時間単価、補正ルール、年間集計の開始月を設定する(黄色セルを自社の実数に変更)
B8: 効果額記録 | C8: 改善・成果を1件ずつ記録する。青字が入力、黒字は自動計算。部署・担当者・効果種別・区分・承認状況はプルダウンで選ぶ
B9: マスタ | C9: プルダウンの選択肢(部署・担当者・効果種別・区分・承認状況)。人や部署が増えたらここに追記する
B10: 運用部ファネル | C10: 求人掲載→応募→面談→成約の月次実績。応募単価と応募1件の粗利を出し、基準値の検証に使う
B11: 月次集計 | C11: 対象月を入れると、承認済の記録を部署別・効果種別・担当者別に集計し、インセンティブ原資を出す
B12: 年間集計 | C12: 部署別の補正後効果額を12か月並べて表示する
B13: 業務分類 | C13: 効果額の4分類と、部署別の測り方の例
B15: 効果額の4分類と入力のしかた
B16: ①収益貢献 | C16: 改善前=前の件数 / 改善後=後の件数 / 回数=1(または期間数) / 単価=1件の粗利(基準値の応募1件の価値など)
B17: ②コスト削減 | C17: 改善前=前の費用 / 改善後=後の費用 / 回数=月数など / 単価=1
B18: ③時間創出 | C18: 改善前=前の所要時間(h) / 改善後=後の所要時間(h) / 回数=月の実施回数 / 単価=時間単価(浮いた時間が営業に回るなら営業の時間あたり粗利)
B19: ④リスク回避 | C19: 改善前=発生確率(前) / 改善後=発生確率(後) / 回数=想定損失額 / 単価=1
B21: 補正ルール(給与と連動させるための安全策)
B22: 貢献度係数 | C22: 他部署や外部要因の影響を考えて、計算額に掛ける係数(初期値50%)
B23: 実現係数 | C23: 区分が「削減時間のみ」のときに掛ける係数。浮いた時間が実際に使われたら区分を「実現済」に変える(係数100%)
B24: 上限 | C24: 1件あたりの効果額の上限。上限で切った行は効果額記録で橙色になる
B25: インセンティブ率 | C25: 補正後効果額のうち報酬原資にする割合。業務委託は時給への加算として運用する
B26: 承認 | C26: 月次集計・年間集計に入るのは承認状況が「承認済」の行だけ。未承認の件数は月次集計の上部に出る
B28: ルール
B29: ベースライン | C29: 改善前の数字は事前に記録し、後から変えない
B30: 根拠 | C30: 根拠資料がない効果は計上しない。根拠・資料の列に出典を書く
B32: 注意
B33: 仮の値 | C33: 基準値シートの数字、効果額記録の例3行、運用部ファネルの数字は仮の値。自社の実績に差し替える

Sheet 基準値
B2: 基準値
B3: 黄色セル(青字)が入力欄。数字は仮の値なので自社の実績に差し替える
B5: ① 応募1件の価値(運用部の効果額に使う)
B6: 直近の粗利総額(月・円) | C6: 6000000 | D6: 営業部の成約による粗利。仮の値
B7: 同期間の応募総数(件) | C7: 2000 | D7: 仮の値
B8: 応募1件の価値(円) | C8: =IF(C7=0,0,C6/C7) | D8: 粗利総額 ÷ 応募総数
B10: ② 営業の時間あたり粗利(営業事務が営業の時間を確保した価値に使う)
B11: 営業部の月間粗利(円) | C11: 6000000 | D11: 仮の値
B12: 営業部の月間稼働時間(h) | C12: 1200 | D12: 架電・応募者対応にあてた時間。仮の値
B13: 営業の時間あたり粗利(円/h) | C13: =IF(C12=0,0,C11/C12) | D13: 月間粗利 ÷ 稼働時間
B15: ③ 時間単価(時間創出の換算に使う)
B16: 業務委託の時給(円) | C16: 1200 | D16: 仮の値
B17: 正社員の月給(会社負担総額・円) | C17: 400000 | D17: 給与+社会保険料など。仮の値
B18: 正社員の月間稼働時間(h) | C18: 160 | D18: 仮の値
B19: 正社員の時間単価(円/h) | C19: =IF(C18=0,0,C17/C18) | D19: 月給 ÷ 稼働時間
B21: ④ 補正ルール
B22: 貢献度係数 | C22: 0.5 | D22: 他の要因を差し引いた貢献の割合
B23: 実現係数(削減時間のみの場合) | C23: 0.5 | D23: 浮いた時間の使い道が確認できていない場合に掛ける
B24: 1件あたり効果額の上限(円) | C24: 500000 | D24: 水増し防止
B25: インセンティブ率 | C25: 0.15 | D25: 補正後効果額のうち報酬原資にする割合
B27: ⑤ 集計の設定
B28: 年間集計の開始月 | C28: 46113 | D28: 期首の月の1日を入れる

Sheet マスタ
B2: マスタ
B3: プルダウンの選択肢。青字の欄に追記・修正する(部署は10件、担当者は30件まで)
B4: 部署 | D4: 担当者 | E4: 所属部署 | G4: 効果種別 | I4: 区分 | K4: 承認状況
B5: 運用部 | D5: 田中 | E5: 運用部 | G5: ①収益貢献 | I5: 実現済 | K5: 未承認
B6: 営業事務 | D6: 佐藤 | E6: 営業事務 | G6: ②コスト削減 | I6: 削減時間のみ | K6: 承認済
B7: 総務 | D7: 鈴木 | E7: 総務 | G7: ③時間創出 | K7: 差戻し
B8: 営業部 | G8: ④リスク回避

Sheet 効果額記録
A1: 効果額記録
A2: 青字=入力 / 黒字=自動計算。最初の3行は記入例(仮の値)。集計に入るのは承認状況が「承認済」の行だけ
A4: 日付 | B4: 対象月 | C4: 部署 | D4: 担当者 | E4: 業務・改善内容 | F4: 効果種別 | G4: 区分 | H4: 改善前 | I4: 改善後 | J4: 回数 | K4: 単価(円) | L4: 計算効果額(円) | M4: 貢献度係数 | N4: 実現係数 | O4: 補正額・上限前(円) | P4: 補正後効果額(円) | Q4: 承認状況 | R4: 承認者 | S4: 根拠・資料
A5: 46297 | B5: {=IF(A5:A304="","",DATE(YEAR(A5:A304),MONTH(A5:A304),1))} | C5: 運用部 | D5: 田中 | E5: 求人原稿の改善で応募数が増加 | F5: ①収益貢献 | G5: 実現済 | H5: 400 | I5: 450 | J5: 1 | K5: =基準値!$C$8 | L5: {=IF((F5:F304="")+(J5:J304="")+(K5:K304=""),"",IF(F5:F304="①収益貢献",I5:I304-H5:H304,H5:H304-I5:I304)*J5:J304*K5:K304)} | M5: {=IF(L5:L304="","",基準値!$C$22)} | N5: {=IF(L5:L304="","",IF(G5:G304="削減時間のみ",基準値!$C$23,1))} | O5: {=IF(L5:L304="","",L5:L304*M5:M304*N5:N304)} | P5: {=IF(O5:O304="","",IF(O5:O304>基準値!$C$24,基準値!$C$24,O5:O304))} | Q5: 承認済 | R5: 山本 | S5: 媒体管理画面の応募数(9月→10月)
A6: 46300 | C6: 営業事務 | D6: 佐藤 | E6: 見積入力のテンプレ化 | F6: ③時間創出 | G6: 削減時間のみ | H6: 0.5 | I6: 0.2 | J6: 80 | K6: =基準値!$C$13 | Q6: 承認済 | R6: 山本 | S6: 作業ログ(1件30分→12分)
A7: 46302 | C7: 総務 | D7: 鈴木 | E7: 通信契約の見直し | F7: ②コスト削減 | G7: 実現済 | H7: 30000 | I7: 22000 | J7: 12 | K7: 1 | Q7: 承認済 | R7: 山本 | S7: 契約書・請求書

Sheet 運用部ファネル
A1: 運用部ファネル(月次)
A2: 青字=入力。数字は仮の値。応募単価と応募1件の粗利を出し、基準値の検証に使う
A4: 月 | B4: 掲載数 | C4: 応募数 | D4: 面談数 | E4: 成約数 | F4: 粗利(円) | G4: 媒体費(円) | H4: 掲載1件あたり応募数 | I4: 面談率(面談÷応募) | J4: 成約率(成約÷面談) | K4: 応募単価(円) | L4: 応募1件の粗利(円)
A5: 46143 | B5: 300 | C5: 1700 | D5: 640 | E5: 128 | F5: 5400000 | G5: 900000 | H5: {=IF((C5:C28="")+(B5:B28=""),"",IF(B5:B28=0,0,C5:C28/B5:B28))} | I5: {=IF((D5:D28="")+(C5:C28=""),"",IF(C5:C28=0,0,D5:D28/C5:C28))} | J5: {=IF((E5:E28="")+(D5:D28=""),"",IF(D5:D28=0,0,E5:E28/D5:D28))} | K5: {=IF((G5:G28="")+(C5:C28=""),"",IF(C5:C28=0,0,G5:G28/C5:C28))} | L5: {=IF((F5:F28="")+(C5:C28=""),"",IF(C5:C28=0,0,F5:F28/C5:C28))}
A6: 46174 | B6: 320 | C6: 1800 | D6: 700 | E6: 135 | F6: 5700000 | G6: 950000
A7: 46204 | B7: 310 | C7: 1850 | D7: 690 | E7: 140 | F7: 5800000 | G7: 950000
A8: 46235 | B8: 330 | C8: 1900 | D8: 720 | E8: 142 | F8: 5900000 | G8: 1000000
A9: 46266 | B9: 340 | C9: 2000 | D9: 760 | E9: 150 | F9: 6000000 | G9: 1000000
A10: 46296 | B10: 350

Sheet 月次集計
A1: 月次集計
A2: 対象月に月の1日を入れると、効果額記録のうち承認済の行を集計する
A4: 対象月 | B4: 46296
A5: 未承認・差戻しの件数 | B5: =COUNTIFS(効果額記録!$B:$B,$B$4,効果額記録!$Q:$Q,"<>承認済") | C5: この件数は下の表に入っていない
A7: 部署別
A8: 部署 | B8: 件数 | C8: 計算効果額(円) | D8: 補正後効果額(円) | E8: インセンティブ原資(円)
A9: =IF(マスタ!B5="","",マスタ!B5) | B9: =IF($A9="","",COUNTIFS(効果額記録!$B:$B,$B$4,効果額記録!$Q:$Q,"承認済",効果額記録!$C:$C,$A9)) | C9: =IF($A9="","",SUMIFS(効果額記録!$L:$L,効果額記録!$B:$B,$B$4,効果額記録!$Q:$Q,"承認済",効果額記録!$C:$C,$A9)) | D9: =IF($A9="","",SUMIFS(効果額記録!$P:$P,効果額記録!$B:$B,$B$4,効果額記録!$Q:$Q,"承認済",効果額記録!$C:$C,$A9)) | E9: =IF($A9="","",D9*基準値!$C$25)
A10: =IF(マスタ!B6="","",マスタ!B6) | B10: =IF($A10="","",COUNTIFS(効果額記録!$B:$B,$B$4,効果額記録!$Q:$Q,"承認済",効果額記録!$C:$C,$A10)) | C10: =IF($A10="","",SUMIFS(効果額記録!$L:$L,効果額記録!$B:$B,$B$4,効果額記録!$Q:$Q,"承認済",効果額記録!$C:$C,$A10)) | D10: =IF($A10="","",SUMIFS(効果額記録!$P:$P,効果額記録!$B:$B,$B$4,効果額記録!$Q:$Q,"承認済",効果額記録!$C:$C,$A10)) | E10: =IF($A10="","",D10*基準値!$C$25)
A11: =IF(マスタ!B7="","",マスタ!B7) | B11: =IF($A11="","",COUNTIFS(効果額記録!$B:$B,$B$4,効果額記録!$Q:$Q,"承認済",効果額記録!$C:$C,$A11)) | C11: =IF($A11="","",SUMIFS(効果額記録!$L:$L,効果額記録!$B:$B,$B$4,効果額記録!$Q:$Q,"承認済",効果額記録!$C:$C,$A11)) | D11: =IF($A11="","",SUMIFS(効果額記録!$P:$P,効果額記録!$B:$B,$B$4,効果額記録!$Q:$Q,"承認済",効果額記録!$C:$C,$A11)) | E11: =IF($A11="","",D11*基準値!$C$25)
A12: =IF(マスタ!B8="","",マスタ!B8) | B12: =IF($A12="","",COUNTIFS(効果額記録!$B:$B,$B$4,効果額記録!$Q:$Q,"承認済",効果額記録!$C:$C,$A12)) | C12: =IF($A12="","",SUMIFS(効果額記録!$L:$L,効果額記録!$B:$B,$B$4,効果額記録!$Q:$Q,"承認済",効果額記録!$C:$C,$A12)) | D12: =IF($A12="","",SUMIFS(効果額記録!$P:$P,効果額記録!$B:$B,$B$4,効果額記録!$Q:$Q,"承認済",効果額記録!$C:$C,$A12)) | E12: =IF($A12="","",D12*基準値!$C$25)
A13: =IF(マスタ!B9="","",マスタ!B9) | B13: =IF($A13="","",COUNTIFS(効果額記録!$B:$B,$B$4,効果額記録!$Q:$Q,"承認済",効果額記録!$C:$C,$A13)) | C13: =IF($A13="","",SUMIFS(効果額記録!$L:$L,効果額記録!$B:$B,$B$4,効果額記録!$Q:$Q,"承認済",効果額記録!$C:$C,$A13)) | D13: =IF($A13="","",SUMIFS(効果額記録!$P:$P,効果額記録!$B:$B,$B$4,効果額記録!$Q:$Q,"承認済",効果額記録!$C:$C,$A13)) | E13: =IF($A13="","",D13*基準値!$C$25)
A14: =IF(マスタ!B10="","",マスタ!B10) | B14: =IF($A14="","",COUNTIFS(効果額記録!$B:$B,$B$4,効果額記録!$Q:$Q,"承認済",効果額記録!$C:$C,$A14)) | C14: =IF($A14="","",SUMIFS(効果額記録!$L:$L,効果額記録!$B:$B,$B$4,効果額記録!$Q:$Q,"承認済",効果額記録!$C:$C,$A14)) | D14: =IF($A14="","",SUMIFS(効果額記録!$P:$P,効果額記録!$B:$B,$B$4,効果額記録!$Q:$Q,"承認済",効果額記録!$C:$C,$A14)) | E14: =IF($A14="","",D14*基準値!$C$25)
A15: =IF(マスタ!B11="","",マスタ!B11) | B15: =IF($A15="","",COUNTIFS(効果額記録!$B:$B,$B$4,効果額記録!$Q:$Q,"承認済",効果額記録!$C:$C,$A15)) | C15: =IF($A15="","",SUMIFS(効果額記録!$L:$L,効果額記録!$B:$B,$B$4,効果額記録!$Q:$Q,"承認済",効果額記録!$C:$C,$A15)) | D15: =IF($A15="","",SUMIFS(効果額記録!$P:$P,効果額記録!$B:$B,$B$4,効果額記録!$Q:$Q,"承認済",効果額記録!$C:$C,$A15)) | E15: =IF($A15="","",D15*基準値!$C$25)
A16: =IF(マスタ!B12="","",マスタ!B12) | B16: =IF($A16="","",COUNTIFS(効果額記録!$B:$B,$B$4,効果額記録!$Q:$Q,"承認済",効果額記録!$C:$C,$A16)) | C16: =IF($A16="","",SUMIFS(効果額記録!$L:$L,効果額記録!$B:$B,$B$4,効果額記録!$Q:$Q,"承認済",効果額記録!$C:$C,$A16)) | D16: =IF($A16="","",SUMIFS(効果額記録!$P:$P,効果額記録!$B:$B,$B$4,効果額記録!$Q:$Q,"承認済",効果額記録!$C:$C,$A16)) | E16: =IF($A16="","",D16*基準値!$C$25)
A17: =IF(マスタ!B13="","",マスタ!B13) | B17: =IF($A17="","",COUNTIFS(効果額記録!$B:$B,$B$4,効果額記録!$Q:$Q,"承認済",効果額記録!$C:$C,$A17)) | C17: =IF($A17="","",SUMIFS(効果額記録!$L:$L,効果額記録!$B:$B,$B$4,効果額記録!$Q:$Q,"承認済",効果額記録!$C:$C,$A17)) | D17: =IF($A17="","",SUMIFS(効果額記録!$P:$P,効果額記録!$B:$B,$B$4,効果額記録!$Q:$Q,"承認済",効果額記録!$C:$C,$A17)) | E17: =IF($A17="","",D17*基準値!$C$25)
A18: =IF(マスタ!B14="","",マスタ!B14) | B18: =IF($A18="","",COUNTIFS(効果額記録!$B:$B,$B$4,効果額記録!$Q:$Q,"承認済",効果額記録!$C:$C,$A18)) | C18: =IF($A18="","",SUMIFS(効果額記録!$L:$L,効果額記録!$B:$B,$B$4,効果額記録!$Q:$Q,"承認済",効果額記録!$C:$C,$A18)) | D18: =IF($A18="","",SUMIFS(効果額記録!$P:$P,効果額記録!$B:$B,$B$4,効果額記録!$Q:$Q,"承認済",効果額記録!$C:$C,$A18)) | E18: =IF($A18="","",D18*基準値!$C$25)
A19: 合計 | B19: =SUM(B9:B18) | C19: =SUM(C9:C18) | D19: =SUM(D9:D18) | E19: =SUM(E9:E18)
A21: 効果種別
A22: 効果種別 | B22: 件数 | C22: 計算効果額(円) | D22: 補正後効果額(円) | E22: インセンティブ原資(円)
A23: =マスタ!G5 | B23: =COUNTIFS(効果額記録!$B:$B,$B$4,効果額記録!$Q:$Q,"承認済",効果額記録!$F:$F,$A23) | C23: =SUMIFS(効果額記録!$L:$L,効果額記録!$B:$B,$B$4,効果額記録!$Q:$Q,"承認済",効果額記録!$F:$F,$A23) | D23: =SUMIFS(効果額記録!$P:$P,効果額記録!$B:$B,$B$4,効果額記録!$Q:$Q,"承認済",効果額記録!$F:$F,$A23) | E23: =D23*基準値!$C$25
A24: =マスタ!G6 | B24: =COUNTIFS(効果額記録!$B:$B,$B$4,効果額記録!$Q:$Q,"承認済",効果額記録!$F:$F,$A24) | C24: =SUMIFS(効果額記録!$L:$L,効果額記録!$B:$B,$B$4,効果額記録!$Q:$Q,"承認済",効果額記録!$F:$F,$A24) | D24: =SUMIFS(効果額記録!$P:$P,効果額記録!$B:$B,$B$4,効果額記録!$Q:$Q,"承認済",効果額記録!$F:$F,$A24) | E24: =D24*基準値!$C$25
A25: =マスタ!G7 | B25: =COUNTIFS(効果額記録!$B:$B,$B$4,効果額記録!$Q:$Q,"承認済",効果額記録!$F:$F,$A25) | C25: =SUMIFS(効果額記録!$L:$L,効果額記録!$B:$B,$B$4,効果額記録!$Q:$Q,"承認済",効果額記録!$F:$F,$A25) | D25: =SUMIFS(効果額記録!$P:$P,効果額記録!$B:$B,$B$4,効果額記録!$Q:$Q,"承認済",効果額記録!$F:$F,$A25) | E25: =D25*基準値!$C$25
A26: =マスタ!G8 | B26: =COUNTIFS(効果額記録!$B:$B,$B$4,効果額記録!$Q:$Q,"承認済",効果額記録!$F:$F,$A26) | C26: =SUMIFS(効果額記録!$L:$L,効果額記録!$B:$B,$B$4,効果額記録!$Q:$Q,"承認済",効果額記録!$F:$F,$A26) | D26: =SUMIFS(効果額記録!$P:$P,効果額記録!$B:$B,$B$4,効果額記録!$Q:$Q,"承認済",効果額記録!$F:$F,$A26) | E26: =D26*基準値!$C$25
A27: 合計 | B27: =SUM(B23:B26) | C27: =SUM(C23:C26) | D27: =SUM(D23:D26) | E27: =SUM(E23:E26)
A29: 担当者別
A30: 担当者 | B30: 所属部署 | C30: 件数 | D30: 計算効果額(円) | E30: 補正後効果額(円) | F30: インセンティブ原資(円)
A31: =IF(マスタ!D5="","",マスタ!D5) | B31: =IF(マスタ!E5="","",マスタ!E5) | C31: =IF($A31="","",COUNTIFS(効果額記録!$B:$B,$B$4,効果額記録!$Q:$Q,"承認済",効果額記録!$D:$D,$A31)) | D31: =IF($A31="","",SUMIFS(効果額記録!$L:$L,効果額記録!$B:$B,$B$4,効果額記録!$Q:$Q,"承認済",効果額記録!$D:$D,$A31)) | E31: =IF($A31="","",SUMIFS(効果額記録!$P:$P,効果額記録!$B:$B,$B$4,効果額記録!$Q:$Q,"承認済",効果額記録!$D:$D,$A31)) | F31: =IF($A31="","",E31*基準値!$C$25)
A32: =IF(マスタ!D6="","",マスタ!D6) | B32: =IF(マスタ!E6="","",マスタ!E6) | C32: =IF($A32="","",COUNTIFS(効果額記録!$B:$B,$B$4,効果額記録!$Q:$Q,"承認済",効果額記録!$D:$D,$A32)) | D32: =IF($A32="","",SUMIFS(効果額記録!$L:$L,効果額記録!$B:$B,$B$4,効果額記録!$Q:$Q,"承認済",効果額記録!$D:$D,$A32)) | E32: =IF($A32="","",SUMIFS(効果額記録!$P:$P,効果額記録!$B:$B,$B$4,効果額記録!$Q:$Q,"承認済",効果額記録!$D:$D,$A32)) | F32: =IF($A32="","",E32*基準値!$C$25)
A33: =IF(マスタ!D7="","",マスタ!D7) | B33: =IF(マスタ!E7="","",マスタ!E7) | C33: =IF($A33="","",COUNTIFS(効果額記録!$B:$B,$B$4,効果額記録!$Q:$Q,"承認済",効果額記録!$D:$D,$A33)) | D33: =IF($A33="","",SUMIFS(効果額記録!$L:$L,効果額記録!$B:$B,$B$4,効果額記録!$Q:$Q,"承認済",効果額記録!$D:$D,$A33)) | E33: =IF($A33="","",SUMIFS(効果額記録!$P:$P,効果額記録!$B:$B,$B$4,効果額記録!$Q:$Q,"承認済",効果額記録!$D:$D,$A33)) | F33: =IF($A33="","",E33*基準値!$C$25)
A34: =IF(マスタ!D8="","",マスタ!D8) | B34: =IF(マスタ!E8="","",マスタ!E8) | C34: =IF($A34="","",COUNTIFS(効果額記録!$B:$B,$B$4,効果額記録!$Q:$Q,"承認済",効果額記録!$D:$D,$A34)) | D34: =IF($A34="","",SUMIFS(効果額記録!$L:$L,効果額記録!$B:$B,$B$4,効果額記録!$Q:$Q,"承認済",効果額記録!$D:$D,$A34)) | E34: =IF($A34="","",SUMIFS(効果額記録!$P:$P,効果額記録!$B:$B,$B$4,効果額記録!$Q:$Q,"承認済",効果額記録!$D:$D,$A34)) | F34: =IF($A34="","",E34*基準値!$C$25)
A35: =IF(マスタ!D9="","",マスタ!D9) | B35: =IF(マスタ!E9="","",マスタ!E9) | C35: =IF($A35="","",COUNTIFS(効果額記録!$B:$B,$B$4,効果額記録!$Q:$Q,"承認済",効果額記録!$D:$D,$A35)) | D35: =IF($A35="","",SUMIFS(効果額記録!$L:$L,効果額記録!$B:$B,$B$4,効果額記録!$Q:$Q,"承認済",効果額記録!$D:$D,$A35)) | E35: =IF($A35="","",SUMIFS(効果額記録!$P:$P,効果額記録!$B:$B,$B$4,効果額記録!$Q:$Q,"承認済",効果額記録!$D:$D,$A35)) | F35: =IF($A35="","",E35*基準値!$C$25)
A36: =IF(マスタ!D10="","",マスタ!D10) | B36: =IF(マスタ!E10="","",マスタ!E10) | C36: =IF($A36="","",COUNTIFS(効果額記録!$B:$B,$B$4,効果額記録!$Q:$Q,"承認済",効果額記録!$D:$D,$A36)) | D36: =IF($A36="","",SUMIFS(効果額記録!$L:$L,効果額記録!$B:$B,$B$4,効果額記録!$Q:$Q,"承認済",効果額記録!$D:$D,$A36)) | E36: =IF($A36="","",SUMIFS(効果額記録!$P:$P,効果額記録!$B:$B,$B$4,効果額記録!$Q:$Q,"承認済",効果額記録!$D:$D,$A36)) | F36: =IF($A36="","",E36*基準値!$C$25)
A37: =IF(マスタ!D11="","",マスタ!D11) | B37: =IF(マスタ!E11="","",マスタ!E11) | C37: =IF($A37="","",COUNTIFS(効果額記録!$B:$B,$B$4,効果額記録!$Q:$Q,"承認済",効果額記録!$D:$D,$A37)) | D37: =IF($A37="","",SUMIFS(効果額記録!$L:$L,効果額記録!$B:$B,$B$4,効果額記録!$Q:$Q,"承認済",効果額記録!$D:$D,$A37)) | E37: =IF($A37="","",SUMIFS(効果額記録!$P:$P,効果額記録!$B:$B,$B$4,効果額記録!$Q:$Q,"承認済",効果額記録!$D:$D,$A37)) | F37: =IF($A37="","",E37*基準値!$C$25)
A38: =IF(マスタ!D12="","",マスタ!D12) | B38: =IF(マスタ!E12="","",マスタ!E12) | C38: =IF($A38="","",COUNTIFS(効果額記録!$B:$B,$B$4,効果額記録!$Q:$Q,"承認済",効果額記録!$D:$D,$A38)) | D38: =IF($A38="","",SUMIFS(効果額記録!$L:$L,効果額記録!$B:$B,$B$4,効果額記録!$Q:$Q,"承認済",効果額記録!$D:$D,$A38)) | E38: =IF($A38="","",SUMIFS(効果額記録!$P:$P,効果額記録!$B:$B,$B$4,効果額記録!$Q:$Q,"承認済",効果額記録!$D:$D,$A38)) | F38: =IF($A38="","",E38*基準値!$C$25)
A39: =IF(マスタ!D13="","",マスタ!D13) | B39: =IF(マスタ!E13="","",マスタ!E13) | C39: =IF($A39="","",COUNTIFS(効果額記録!$B:$B,$B$4,効果額記録!$Q:$Q,"承認済",効果額記録!$D:$D,$A39)) | D39: =IF($A39="","",SUMIFS(効果額記録!$L:$L,効果額記録!$B:$B,$B$4,効果額記録!$Q:$Q,"承認済",効果額記録!$D:$D,$A39)) | E39: =IF($A39="","",SUMIFS(効果額記録!$P:$P,効果額記録!$B:$B,$B$4,効果額記録!$Q:$Q,"承認済",効果額記録!$D:$D,$A39)) | F39: =IF($A39="","",E39*基準値!$C$25)
A40: =IF(マスタ!D14="","",マスタ!D14) | B40: =IF(マスタ!E14="","",マスタ!E14) | C40: =IF($A40="","",COUNTIFS(効果額記録!$B:$B,$B$4,効果額記録!$Q:$Q,"承認済",効果額記録!$D:$D,$A40)) | D40: =IF($A40="","",SUMIFS(効果額記録!$L:$L,効果額記録!$B:$B,$B$4,効果額記録!$Q:$Q,"承認済",効果額記録!$D:$D,$A40)) | E40: =IF($A40="","",SUMIFS(効果額記録!$P:$P,効果額記録!$B:$B,$B$4,効果額記録!$Q:$Q,"承認済",効果額記録!$D:$D,$A40)) | F40: =IF($A40="","",E40*基準値!$C$25)
A41: =IF(マスタ!D15="","",マスタ!D15) | B41: =IF(マスタ!E15="","",マスタ!E15) | C41: =IF($A41="","",COUNTIFS(効果額記録!$B:$B,$B$4,効果額記録!$Q:$Q,"承認済",効果額記録!$D:$D,$A41)) | D41: =IF($A41="","",SUMIFS(効果額記録!$L:$L,効果額記録!$B:$B,$B$4,効果額記録!$Q:$Q,"承認済",効果額記録!$D:$D,$A41)) | E41: =IF($A41="","",SUMIFS(効果額記録!$P:$P,効果額記録!$B:$B,$B$4,効果額記録!$Q:$Q,"承認済",効果額記録!$D:$D,$A41)) | F41: =IF($A41="","",E41*基準値!$C$25)
A42: =IF(マスタ!D16="","",マスタ!D16) | B42: =IF(マスタ!E16="","",マスタ!E16) | C42: =IF($A42="","",COUNTIFS(効果額記録!$B:$B,$B$4,効果額記録!$Q:$Q,"承認済",効果額記録!$D:$D,$A42)) | D42: =IF($A42="","",SUMIFS(効果額記録!$L:$L,効果額記録!$B:$B,$B$4,効果額記録!$Q:$Q,"承認済",効果額記録!$D:$D,$A42)) | E42: =IF($A42="","",SUMIFS(効果額記録!$P:$P,効果額記録!$B:$B,$B$4,効果額記録!$Q:$Q,"承認済",効果額記録!$D:$D,$A42)) | F42: =IF($A42="","",E42*基準値!$C$25)
... A60: =IF(マスタ!D34="","",マスタ!D34) | B60: =IF(マスタ!E34="","",マスタ!E34) | C60: =IF($A60="","",COUNTIFS(効果額記録!$B:$B,$B$4,効果額記録!$Q:$Q,"承認済",効果額記録!$D:$D,$A60)) | D60: =IF($A60="","",SUMIFS(効果額記録!$L:$L,効果額記録!$B:$B,$B$4,効果額記録!$Q:$Q,"承認済",効果額記録!$D:$D,$A60)) | E60: =IF($A60="","",SUMIFS(効果額記録!$P:$P,効果額記録!$B:$B,$B$4,効果額記録!$Q:$Q,"承認済",効果額記録!$D:$D,$A60)) | F60: =IF($A60="","",E60*基準値!$C$25)
A61: 合計 | C61: =SUM(C31:C60) | D61: =SUM(D31:D60) | E61: =SUM(E31:E60) | F61: =SUM(F31:F60)

Sheet 年間集計
A1: 年間集計(補正後効果額・承認済のみ)
A2: 開始月は基準値シートの「年間集計の開始月」で変える
A4: 部署 | B4: =基準値!$C$28 | C4: =EDATE(B4,1) | D4: =EDATE(C4,1) | E4: =EDATE(D4,1) | F4: =EDATE(E4,1) | G4: =EDATE(F4,1) | H4: =EDATE(G4,1) | I4: =EDATE(H4,1) | J4: =EDATE(I4,1) | ... M4: =EDATE(L4,1) | N4: 年間合計
A5: =IF(マスタ!B5="","",マスタ!B5) | B5: =IF($A5="","",SUMIFS(効果額記録!$P:$P,効果額記録!$C:$C,$A5,効果額記録!$B:$B,B$4,効果額記録!$Q:$Q,"承認済")) | C5: =IF($A5="","",SUMIFS(効果額記録!$P:$P,効果額記録!$C:$C,$A5,効果額記録!$B:$B,C$4,効果額記録!$Q:$Q,"承認済")) | D5: =IF($A5="","",SUMIFS(効果額記録!$P:$P,効果額記録!$C:$C,$A5,効果額記録!$B:$B,D$4,効果額記録!$Q:$Q,"承認済")) | E5: =IF($A5="","",SUMIFS(効果額記録!$P:$P,効果額記録!$C:$C,$A5,効果額記録!$B:$B,E$4,効果額記録!$Q:$Q,"承認済")) | F5: =IF($A5="","",SUMIFS(効果額記録!$P:$P,効果額記録!$C:$C,$A5,効果額記録!$B:$B,F$4,効果額記録!$Q:$Q,"承認済")) | G5: =IF($A5="","",SUMIFS(効果額記録!$P:$P,効果額記録!$C:$C,$A5,効果額記録!$B:$B,G$4,効果額記録!$Q:$Q,"承認済")) | H5: =IF($A5="","",SUMIFS(効果額記録!$P:$P,効果額記録!$C:$C,$A5,効果額記録!$B:$B,H$4,効果額記録!$Q:$Q,"承認済")) | I5: =IF($A5="","",SUMIFS(効果額記録!$P:$P,効果額記録!$C:$C,$A5,効果額記録!$B:$B,I$4,効果額記録!$Q:$Q,"承認済")) | ... M5: =IF($A5="","",SUMIFS(効果額記録!$P:$P,効果額記録!$C:$C,$A5,効果額記録!$B:$B,M$4,効果額記録!$Q:$Q,"承認済")) | N5: =IF($A5="","",SUM(B5:M5))
A6: =IF(マスタ!B6="","",マスタ!B6) | B6: =IF($A6="","",SUMIFS(効果額記録!$P:$P,効果額記録!$C:$C,$A6,効果額記録!$B:$B,B$4,効果額記録!$Q:$Q,"承認済")) | C6: =IF($A6="","",SUMIFS(効果額記録!$P:$P,効果額記録!$C:$C,$A6,効果額記録!$B:$B,C$4,効果額記録!$Q:$Q,"承認済")) | D6: =IF($A6="","",SUMIFS(効果額記録!$P:$P,効果額記録!$C:$C,$A6,効果額記録!$B:$B,D$4,効果額記録!$Q:$Q,"承認済")) | E6: =IF($A6="","",SUMIFS(効果額記録!$P:$P,効果額記録!$C:$C,$A6,効果額記録!$B:$B,E$4,効果額記録!$Q:$Q,"承認済")) | F6: =IF($A6="","",SUMIFS(効果額記録!$P:$P,効果額記録!$C:$C,$A6,効果額記録!$B:$B,F$4,効果額記録!$Q:$Q,"承認済")) | G6: =IF($A6="","",SUMIFS(効果額記録!$P:$P,効果額記録!$C:$C,$A6,効果額記録!$B:$B,G$4,効果額記録!$Q:$Q,"承認済")) | H6: =IF($A6="","",SUMIFS(効果額記録!$P:$P,効果額記録!$C:$C,$A6,効果額記録!$B:$B,H$4,効果額記録!$Q:$Q,"承認済")) | I6: =IF($A6="","",SUMIFS(効果額記録!$P:$P,効果額記録!$C:$C,$A6,効果額記録!$B:$B,I$4,効果額記録!$Q:$Q,"承認済")) | ... M6: =IF($A6="","",SUMIFS(効果額記録!$P:$P,効果額記録!$C:$C,$A6,効果額記録!$B:$B,M$4,効果額記録!$Q:$Q,"承認済")) | N6: =IF($A6="","",SUM(B6:M6))
A7: =IF(マスタ!B7="","",マスタ!B7) | B7: =IF($A7="","",SUMIFS(効果額記録!$P:$P,効果額記録!$C:$C,$A7,効果額記録!$B:$B,B$4,効果額記録!$Q:$Q,"承認済")) | C7: =IF($A7="","",SUMIFS(効果額記録!$P:$P,効果額記録!$C:$C,$A7,効果額記録!$B:$B,C$4,効果額記録!$Q:$Q,"承認済")) | D7: =IF($A7="","",SUMIFS(効果額記録!$P:$P,効果額記録!$C:$C,$A7,効果額記録!$B:$B,D$4,効果額記録!$Q:$Q,"承認済")) | E7: =IF($A7="","",SUMIFS(効果額記録!$P:$P,効果額記録!$C:$C,$A7,効果額記録!$B:$B,E$4,効果額記録!$Q:$Q,"承認済")) | F7: =IF($A7="","",SUMIFS(効果額記録!$P:$P,効果額記録!$C:$C,$A7,効果額記録!$B:$B,F$4,効果額記録!$Q:$Q,"承認済")) | G7: =IF($A7="","",SUMIFS(効果額記録!$P:$P,効果額記録!$C:$C,$A7,効果額記録!$B:$B,G$4,効果額記録!$Q:$Q,"承認済")) | H7: =IF($A7="","",SUMIFS(効果額記録!$P:$P,効果額記録!$C:$C,$A7,効果額記録!$B:$B,H$4,効果額記録!$Q:$Q,"承認済")) | I7: =IF($A7="","",SUMIFS(効果額記録!$P:$P,効果額記録!$C:$C,$A7,効果額記録!$B:$B,I$4,効果額記録!$Q:$Q,"承認済")) | ... M7: =IF($A7="","",SUMIFS(効果額記録!$P:$P,効果額記録!$C:$C,$A7,効果額記録!$B:$B,M$4,効果額記録!$Q:$Q,"承認済")) | N7: =IF($A7="","",SUM(B7:M7))
A8: =IF(マスタ!B8="","",マスタ!B8) | B8: =IF($A8="","",SUMIFS(効果額記録!$P:$P,効果額記録!$C:$C,$A8,効果額記録!$B:$B,B$4,効果額記録!$Q:$Q,"承認済")) | C8: =IF($A8="","",SUMIFS(効果額記録!$P:$P,効果額記録!$C:$C,$A8,効果額記録!$B:$B,C$4,効果額記録!$Q:$Q,"承認済")) | D8: =IF($A8="","",SUMIFS(効果額記録!$P:$P,効果額記録!$C:$C,$A8,効果額記録!$B:$B,D$4,効果額記録!$Q:$Q,"承認済")) | E8: =IF($A8="","",SUMIFS(効果額記録!$P:$P,効果額記録!$C:$C,$A8,効果額記録!$B:$B,E$4,効果額記録!$Q:$Q,"承認済")) | F8: =IF($A8="","",SUMIFS(効果額記録!$P:$P,効果額記録!$C:$C,$A8,効果額記録!$B:$B,F$4,効果額記録!$Q:$Q,"承認済")) | G8: =IF($A8="","",SUMIFS(効果額記録!$P:$P,効果額記録!$C:$C,$A8,効果額記録!$B:$B,G$4,効果額記録!$Q:$Q,"承認済")) | H8: =IF($A8="","",SUMIFS(効果額記録!$P:$P,効果額記録!$C:$C,$A8,効果額記録!$B:$B,H$4,効果額記録!$Q:$Q,"承認済")) | I8: =IF($A8="","",SUMIFS(効果額記録!$P:$P,効果額記録!$C:$C,$A8,効果額記録!$B:$B,I$4,効果額記録!$Q:$Q,"承認済")) | ... M8: =IF($A8="","",SUMIFS(効果額記録!$P:$P,効果額記録!$C:$C,$A8,効果額記録!$B:$B,M$4,効果額記録!$Q:$Q,"承認済")) | N8: =IF($A8="","",SUM(B8:M8))
A9: =IF(マスタ!B9="","",マスタ!B9) | B9: =IF($A9="","",SUMIFS(効果額記録!$P:$P,効果額記録!$C:$C,$A9,効果額記録!$B:$B,B$4,効果額記録!$Q:$Q,"承認済")) | C9: =IF($A9="","",SUMIFS(効果額記録!$P:$P,効果額記録!$C:$C,$A9,効果額記録!$B:$B,C$4,効果額記録!$Q:$Q,"承認済")) | D9: =IF($A9="","",SUMIFS(効果額記録!$P:$P,効果額記録!$C:$C,$A9,効果額記録!$B:$B,D$4,効果額記録!$Q:$Q,"承認済")) | E9: =IF($A9="","",SUMIFS(効果額記録!$P:$P,効果額記録!$C:$C,$A9,効果額記録!$B:$B,E$4,効果額記録!$Q:$Q,"承認済")) | F9: =IF($A9="","",SUMIFS(効果額記録!$P:$P,効果額記録!$C:$C,$A9,効果額記録!$B:$B,F$4,効果額記録!$Q:$Q,"承認済")) | G9: =IF($A9="","",SUMIFS(効果額記録!$P:$P,効果額記録!$C:$C,$A9,効果額記録!$B:$B,G$4,効果額記録!$Q:$Q,"承認済")) | H9: =IF($A9="","",SUMIFS(効果額記録!$P:$P,効果額記録!$C:$C,$A9,効果額記録!$B:$B,H$4,効果額記録!$Q:$Q,"承認済")) | I9: =IF($A9="","",SUMIFS(効果額記録!$P:$P,効果額記録!$C:$C,$A9,効果額記録!$B:$B,I$4,効果額記録!$Q:$Q,"承認済")) | ... M9: =IF($A9="","",SUMIFS(効果額記録!$P:$P,効果額記録!$C:$C,$A9,効果額記録!$B:$B,M$4,効果額記録!$Q:$Q,"承認済")) | N9: =IF($A9="","",SUM(B9:M9))
A10: =IF(マスタ!B10="","",マスタ!B10) | B10: =IF($A10="","",SUMIFS(効果額記録!$P:$P,効果額記録!$C:$C,$A10,効果額記録!$B:$B,B$4,効果額記録!$Q:$Q,"承認済")) | C10: =IF($A10="","",SUMIFS(効果額記録!$P:$P,効果額記録!$C:$C,$A10,効果額記録!$B:$B,C$4,効果額記録!$Q:$Q,"承認済")) | D10: =IF($A10="","",SUMIFS(効果額記録!$P:$P,効果額記録!$C:$C,$A10,効果額記録!$B:$B,D$4,効果額記録!$Q:$Q,"承認済")) | E10: =IF($A10="","",SUMIFS(効果額記録!$P:$P,効果額記録!$C:$C,$A10,効果額記録!$B:$B,E$4,効果額記録!$Q:$Q,"承認済")) | F10: =IF($A10="","",SUMIFS(効果額記録!$P:$P,効果額記録!$C:$C,$A10,効果額記録!$B:$B,F$4,効果額記録!$Q:$Q,"承認済")) | G10: =IF($A10="","",SUMIFS(効果額記録!$P:$P,効果額記録!$C:$C,$A10,効果額記録!$B:$B,G$4,効果額記録!$Q:$Q,"承認済")) | H10: =IF($A10="","",SUMIFS(効果額記録!$P:$P,効果額記録!$C:$C,$A10,効果額記録!$B:$B,H$4,効果額記録!$Q:$Q,"承認済")) | I10: =IF($A10="","",SUMIFS(効果額記録!$P:$P,効果額記録!$C:$C,$A10,効果額記録!$B:$B,I$4,効果額記録!$Q:$Q,"承認済")) | ... M10: =IF($A10="","",SUMIFS(効果額記録!$P:$P,効果額記録!$C:$C,$A10,効果額記録!$B:$B,M$4,効果額記録!$Q:$Q,"承認済")) | N10: =IF($A10="","",SUM(B10:M10))
A11: =IF(マスタ!B11="","",マスタ!B11) | B11: =IF($A11="","",SUMIFS(効果額記録!$P:$P,効果額記録!$C:$C,$A11,効果額記録!$B:$B,B$4,効果額記録!$Q:$Q,"承認済")) | C11: =IF($A11="","",SUMIFS(効果額記録!$P:$P,効果額記録!$C:$C,$A11,効果額記録!$B:$B,C$4,効果額記録!$Q:$Q,"承認済")) | D11: =IF($A11="","",SUMIFS(効果額記録!$P:$P,効果額記録!$C:$C,$A11,効果額記録!$B:$B,D$4,効果額記録!$Q:$Q,"承認済")) | E11: =IF($A11="","",SUMIFS(効果額記録!$P:$P,効果額記録!$C:$C,$A11,効果額記録!$B:$B,E$4,効果額記録!$Q:$Q,"承認済")) | F11: =IF($A11="","",SUMIFS(効果額記録!$P:$P,効果額記録!$C:$C,$A11,効果額記録!$B:$B,F$4,効果額記録!$Q:$Q,"承認済")) | G11: =IF($A11="","",SUMIFS(効果額記録!$P:$P,効果額記録!$C:$C,$A11,効果額記録!$B:$B,G$4,効果額記録!$Q:$Q,"承認済")) | H11: =IF($A11="","",SUMIFS(効果額記録!$P:$P,効果額記録!$C:$C,$A11,効果額記録!$B:$B,H$4,効果額記録!$Q:$Q,"承認済")) | I11: =IF($A11="","",SUMIFS(効果額記録!$P:$P,効果額記録!$C:$C,$A11,効果額記録!$B:$B,I$4,効果額記録!$Q:$Q,"承認済")) | ... M11: =IF($A11="","",SUMIFS(効果額記録!$P:$P,効果額記録!$C:$C,$A11,効果額記録!$B:$B,M$4,効果額記録!$Q:$Q,"承認済")) | N11: =IF($A11="","",SUM(B11:M11))
A12: =IF(マスタ!B12="","",マスタ!B12) | B12: =IF($A12="","",SUMIFS(効果額記録!$P:$P,効果額記録!$C:$C,$A12,効果額記録!$B:$B,B$4,効果額記録!$Q:$Q,"承認済")) | C12: =IF($A12="","",SUMIFS(効果額記録!$P:$P,効果額記録!$C:$C,$A12,効果額記録!$B:$B,C$4,効果額記録!$Q:$Q,"承認済")) | D12: =IF($A12="","",SUMIFS(効果額記録!$P:$P,効果額記録!$C:$C,$A12,効果額記録!$B:$B,D$4,効果額記録!$Q:$Q,"承認済")) | E12: =IF($A12="","",SUMIFS(効果額記録!$P:$P,効果額記録!$C:$C,$A12,効果額記録!$B:$B,E$4,効果額記録!$Q:$Q,"承認済")) | F12: =IF($A12="","",SUMIFS(効果額記録!$P:$P,効果額記録!$C:$C,$A12,効果額記録!$B:$B,F$4,効果額記録!$Q:$Q,"承認済")) | G12: =IF($A12="","",SUMIFS(効果額記録!$P:$P,効果額記録!$C:$C,$A12,効果額記録!$B:$B,G$4,効果額記録!$Q:$Q,"承認済")) | H12: =IF($A12="","",SUMIFS(効果額記録!$P:$P,効果額記録!$C:$C,$A12,効果額記録!$B:$B,H$4,効果額記録!$Q:$Q,"承認済")) | I12: =IF($A12="","",SUMIFS(効果額記録!$P:$P,効果額記録!$C:$C,$A12,効果額記録!$B:$B,I$4,効果額記録!$Q:$Q,"承認済")) | ... M12: =IF($A12="","",SUMIFS(効果額記録!$P:$P,効果額記録!$C:$C,$A12,効果額記録!$B:$B,M$4,効果額記録!$Q:$Q,"承認済")) | N12: =IF($A12="","",SUM(B12:M12))
A13: =IF(マスタ!B13="","",マスタ!B13) | B13: =IF($A13="","",SUMIFS(効果額記録!$P:$P,効果額記録!$C:$C,$A13,効果額記録!$B:$B,B$4,効果額記録!$Q:$Q,"承認済")) | C13: =IF($A13="","",SUMIFS(効果額記録!$P:$P,効果額記録!$C:$C,$A13,効果額記録!$B:$B,C$4,効果額記録!$Q:$Q,"承認済")) | D13: =IF($A13="","",SUMIFS(効果額記録!$P:$P,効果額記録!$C:$C,$A13,効果額記録!$B:$B,D$4,効果額記録!$Q:$Q,"承認済")) | E13: =IF($A13="","",SUMIFS(効果額記録!$P:$P,効果額記録!$C:$C,$A13,効果額記録!$B:$B,E$4,効果額記録!$Q:$Q,"承認済")) | F13: =IF($A13="","",SUMIFS(効果額記録!$P:$P,効果額記録!$C:$C,$A13,効果額記録!$B:$B,F$4,効果額記録!$Q:$Q,"承認済")) | G13: =IF($A13="","",SUMIFS(効果額記録!$P:$P,効果額記録!$C:$C,$A13,効果額記録!$B:$B,G$4,効果額記録!$Q:$Q,"承認済")) | H13: =IF($A13="","",SUMIFS(効果額記録!$P:$P,効果額記録!$C:$C,$A13,効果額記録!$B:$B,H$4,効果額記録!$Q:$Q,"承認済")) | I13: =IF($A13="","",SUMIFS(効果額記録!$P:$P,効果額記録!$C:$C,$A13,効果額記録!$B:$B,I$4,効果額記録!$Q:$Q,"承認済")) | ... M13: =IF($A13="","",SUMIFS(効果額記録!$P:$P,効果額記録!$C:$C,$A13,効果額記録!$B:$B,M$4,効果額記録!$Q:$Q,"承認済")) | N13: =IF($A13="","",SUM(B13:M13))
A14: =IF(マスタ!B14="","",マスタ!B14) | B14: =IF($A14="","",SUMIFS(効果額記録!$P:$P,効果額記録!$C:$C,$A14,効果額記録!$B:$B,B$4,効果額記録!$Q:$Q,"承認済")) | C14: =IF($A14="","",SUMIFS(効果額記録!$P:$P,効果額記録!$C:$C,$A14,効果額記録!$B:$B,C$4,効果額記録!$Q:$Q,"承認済")) | D14: =IF($A14="","",SUMIFS(効果額記録!$P:$P,効果額記録!$C:$C,$A14,効果額記録!$B:$B,D$4,効果額記録!$Q:$Q,"承認済")) | E14: =IF($A14="","",SUMIFS(効果額記録!$P:$P,効果額記録!$C:$C,$A14,効果額記録!$B:$B,E$4,効果額記録!$Q:$Q,"承認済")) | F14: =IF($A14="","",SUMIFS(効果額記録!$P:$P,効果額記録!$C:$C,$A14,効果額記録!$B:$B,F$4,効果額記録!$Q:$Q,"承認済")) | G14: =IF($A14="","",SUMIFS(効果額記録!$P:$P,効果額記録!$C:$C,$A14,効果額記録!$B:$B,G$4,効果額記録!$Q:$Q,"承認済")) | H14: =IF($A14="","",SUMIFS(効果額記録!$P:$P,効果額記録!$C:$C,$A14,効果額記録!$B:$B,H$4,効果額記録!$Q:$Q,"承認済")) | I14: =IF($A14="","",SUMIFS(効果額記録!$P:$P,効果額記録!$C:$C,$A14,効果額記録!$B:$B,I$4,効果額記録!$Q:$Q,"承認済")) | ... M14: =IF($A14="","",SUMIFS(効果額記録!$P:$P,効果額記録!$C:$C,$A14,効果額記録!$B:$B,M$4,効果額記録!$Q:$Q,"承認済")) | N14: =IF($A14="","",SUM(B14:M14))
A15: 合計 | B15: =SUM(B5:B14) | C15: =SUM(C5:C14) | D15: =SUM(D5:D14) | E15: =SUM(E5:E14) | F15: =SUM(F5:F14) | G15: =SUM(G5:G14) | H15: =SUM(H5:H14) | I15: =SUM(I5:I14) | ... N15: =SUM(N5:N14)
A16: インセンティブ原資 | B16: =B15*基準値!$C$25 | C16: =C15*基準値!$C$25 | D16: =D15*基準値!$C$25 | E16: =E15*基準値!$C$25 | F16: =F15*基準値!$C$25 | G16: =G15*基準値!$C$25 | H16: =H15*基準値!$C$25 | I16: =I15*基準値!$C$25 | ... N16: =N15*基準値!$C$25

Sheet 業務分類
B2: 効果額の4分類と部署別の測り方(例)
B4: 分類 | C4: 意味 | D4: 計算の基本形 | E4: 運用部の例 | F4: 営業事務の例 | G4: 総務の例
B5: ①収益貢献 | C5: 応募・成約が増えた分 | D5: 増えた件数 × 1件あたりの粗利 | E5: 原稿改善で応募数増 / 掲載枠の最適化 | F5: フォロー漏れ防止による成約数増 | G5: (該当少)
B6: ②コスト削減 | C6: 媒体費・外注費などが減った分 | D6: 削減前の費用 − 削減後の費用 | E6: 応募単価(媒体費÷応募数)の改善 / 不要掲載の停止 | F6: 外注・消耗品費の削減 | G6: 契約見直し / 経費削減
B7: ③時間創出 | C7: 他の人の作業時間が浮いた分 | D7: 浮いた時間 × 時間単価 | E7: 掲載作業のテンプレ化・自動化 | F7: 営業が電話に使える時間の確保(営業の時間あたり粗利で換算) | G7: 手続きの効率化
B8: ④リスク回避 | C8: ミスやトラブルを防いだ分 | D8: 想定損失額 × 発生確率の低下分 | E8: 掲載ミス・規約違反による掲載停止の防止 | F8: 入力ミス・二重連絡の防止 | G8: 労務・法務リスクの回避
B10: ※ 数字にしにくい業務は無理に金額にせず「必須業務」として別枠で扱う。
